troi/__init__.py
troi/cli.py
troi/core.py
troi/filters.py
troi/http_request.py
troi/logging_utils.py
troi/loops.py
troi/operations.py
troi/parse_prompt.py
troi/patch.py
troi/playlist.py
troi/plist.py
troi/print_recording.py
troi/recording_search_service.py
troi/service.py
troi/sorts.py
troi/utils.py
troi/content_resolver/__init__.py
troi/content_resolver/artist_search.py
troi/content_resolver/cli.py
troi/content_resolver/content_resolver.py
troi/content_resolver/database.py
troi/content_resolver/duplicates.py
troi/content_resolver/fuzzy_index.py
troi/content_resolver/lb_radio.py
troi/content_resolver/metadata_lookup.py
troi/content_resolver/playlist.py
troi/content_resolver/py_sonic_fix.py
troi/content_resolver/subsonic.py
troi/content_resolver/tag_search.py
troi/content_resolver/top_tags.py
troi/content_resolver/unresolved_recording.py
troi/content_resolver/utils.py
troi/content_resolver/formats/__init__.py
troi/content_resolver/formats/flac.py
troi/content_resolver/formats/m4a.py
troi/content_resolver/formats/mp3.py
troi/content_resolver/formats/ogg_opus.py
troi/content_resolver/formats/ogg_vorbis.py
troi/content_resolver/formats/tag_utils.py
troi/content_resolver/formats/wma.py
troi/content_resolver/model/__init__.py
troi/content_resolver/model/database.py
troi/content_resolver/model/directory.py
troi/content_resolver/model/recording.py
troi/content_resolver/model/tag.py
troi/content_resolver/model/unresolved_recording.py
troi/external/__init__.py
troi/external/gpt.py
troi/listenbrainz/__init__.py
troi/listenbrainz/feedback.py
troi/listenbrainz/listens.py
troi/listenbrainz/recs.py
troi/listenbrainz/stats.py
troi/listenbrainz/user.py
troi/listenbrainz/unused/README.txt
troi/listenbrainz/unused/dataset_fetcher.py
troi/local/periodic_jams_local.py
troi/local/recording_resolver.py
troi/musicbrainz/__init__.py
troi/musicbrainz/mbid_mapping.py
troi/musicbrainz/mbid_reader.py
troi/musicbrainz/recording.py
troi/musicbrainz/recording_lookup.py
troi-2025.8.6.3.dist-info/licenses/LICENSE
troi-2025.8.6.3.dist-info/METADATA
troi-2025.8.6.3.dist-info/WHEEL
troi-2025.8.6.3.dist-info/entry_points.txt
troi-2025.8.6.3.dist-info/top_level.txt
troi-2025.8.6.3.dist-info/RECORD
