Metadata-Version: 2.4
Name: troi
Version: 2025.8.6.3
Summary: ListenBrainz' empathic music recommendation/playlisting engine
Author-email: MetaBrainz Foundation <support@metabrainz.org>
Project-URL: Homepage, https://github.com/metabrainz/troi-recommendation-playground
Project-URL: Documentation, https://troi.readthedocs.io/en/latest/
Project-URL: Releases, https://github.com/metabrainz/troi-recommendation-playground/releases
Project-URL: Issues, https://tickets.metabrainz.org/secure/RapidBoard.jspa?rapidView=14&projectKey=LB#
Classifier: Programming Language :: Python :: 3
Classifier: License :: OSI Approved :: GNU General Public License v3 (GPLv3)
Classifier: Operating System :: OS Independent
Requires-Python: >=3.9
License-File: LICENSE
Requires-Dist: click>=8.0
Requires-Dist: countryinfo>=0.1.2
Requires-Dist: lb_matching_tools>=v2024.01.30.1
Requires-Dist: liblistenbrainz>=v0.6.0
Requires-Dist: more_itertools
Requires-Dist: mutagen==1.46.0
Requires-Dist: peewee>=3.17.0
Requires-Dist: psycopg2-binary>=2.9.3
Requires-Dist: py-sonic>=1.0.2
Requires-Dist: python-dateutil>=2.8.2
Requires-Dist: regex>=2023.6.3
Requires-Dist: requests>=2.31.0
Requires-Dist: scikit-learn>=1.2.1
Requires-Dist: spotipy>=2.22.1
Requires-Dist: tqdm
Requires-Dist: ujson>=5.4.0
Requires-Dist: Unidecode>=1.3.6
Provides-Extra: nmslib
Requires-Dist: nmslib-metabrainz>=2.1.1; extra == "nmslib"
Provides-Extra: tests
Requires-Dist: pytest==7.1.2; extra == "tests"
Requires-Dist: pytest-cov==4.1.0; extra == "tests"
Requires-Dist: requests-mock==1.11.0; extra == "tests"
Provides-Extra: build
Requires-Dist: build; extra == "build"
Provides-Extra: docs
Requires-Dist: Sphinx==5.0.2; extra == "docs"
Requires-Dist: sphinxcontrib-httpdomain==1.8.0; extra == "docs"
Requires-Dist: sphinx_rtd_theme==0.5.1; extra == "docs"
Requires-Dist: docutils==0.17.1; extra == "docs"
Requires-Dist: sphinx-click==4.3.0; extra == "docs"
Dynamic: license-file
